[
  {
    "ContainingType": "TestApplication.Controllers.TestController",
    "Method": "Delete",
    "RelativePath": "api/Test/Delete",
    "HttpMethod": "GET",
    "IsController": true,
    "Order": 0,
    "Parameters": [
      {
        "Name": "Id",
        "Type": "System.Int32",
        "IsRequired": false
      }
    ],
    "ReturnTypes": []
  },
  {
    "ContainingType": "TestApplication.Controllers.TestController",
    "Method": "Insert",
    "RelativePath": "api/Test/Insert",
    "HttpMethod": "GET",
    "IsController": true,
    "Order": 0,
    "Parameters": [
      {
        "Name": "Id",
        "Type": "System.Int32",
        "IsRequired": false
      },
      {
        "Name": "CatageryName",
        "Type": "System.String",
        "IsRequired": false
      },
      {
        "Name": "Name",
        "Type": "System.String",
        "IsRequired": false
      },
      {
        "Name": "lastName",
        "Type": "System.String",
        "IsRequired": false
      },
      {
        "Name": "userName",
        "Type": "System.String",
        "IsRequired": false
      },
      {
        "Name": "dob",
        "Type": "System.DateTime",
        "IsRequired": false
      },
      {
        "Name": "email",
        "Type": "System.String",
        "IsRequired": false
      },
      {
        "Name": "phone",
        "Type": "System.Int32",
        "IsRequired": false
      },
      {
        "Name": "cnic",
        "Type": "System.Int32",
        "IsRequired": false
      },
      {
        "Name": "address",
        "Type": "System.String",
        "IsRequired": false
      },
      {
        "Name": "password",
        "Type": "System.String",
        "IsRequired": false
      },
      {
        "Name": "message",
        "Type": "System.String",
        "IsRequired": false
      },
      {
        "Name": "optionOne",
        "Type": "System.Boolean",
        "IsRequired": false
      },
      {
        "Name": "optionTwo",
        "Type": "System.Boolean",
        "IsRequired": false
      }
    ],
    "ReturnTypes": []
  },
  {
    "ContainingType": "TestApplication.Controllers.TestController",
    "Method": "ReadAll",
    "RelativePath": "api/Test/ReadAll",
    "HttpMethod": "GET",
    "IsController": true,
    "Order": 0,
    "Parameters": [],
    "ReturnTypes": []
  },
  {
    "ContainingType": "TestApplication.Controllers.TestController",
    "Method": "ReadById",
    "RelativePath": "api/Test/ReadById",
    "HttpMethod": "GET",
    "IsController": true,
    "Order": 0,
    "Parameters": [
      {
        "Name": "Id",
        "Type": "System.Int32",
        "IsRequired": false
      }
    ],
    "ReturnTypes": []
  }
]